vrroompy/__init__.py
vrroompy/codec.py
vrroompy/exceptions.py
vrroompy/commands/__init__.py
vrroompy/commands/actions.py
vrroompy/commands/enums.py
vrroompy/commands/input.py
vrroompy/commands/modes.py
vrroompy/commands/network.py
VRROOMpy-1.1.0.dist-info/LICENSE.txt
VRROOMpy-1.1.0.dist-info/METADATA
VRROOMpy-1.1.0.dist-info/WHEEL
VRROOMpy-1.1.0.dist-info/top_level.txt
VRROOMpy-1.1.0.dist-info/RECORD
