Metadata-Version: 2.1
Name: VRROOMpy
Version: 1.1.0
Summary: Package for controlling HDFury VRROOM HDMI switches via Python.
Author-email: Vincent Kocks <engineering@vingenuity.net>
License: GPL-3.0-or-later
Project-URL: Homepage, https://github.com/vingenuity/vrroompy
Project-URL: Bug Tracker, https://github.com/vingenuity/vrroompy/issues
Classifier: Programming Language :: Python :: 3
Classifier: License :: OSI Approved :: GNU General Public License v3 or later (GPLv3+)
Classifier: Operating System :: OS Independent
Requires-Python: >=3.7
License-File: LICENSE.txt
Provides-Extra: dev
Requires-Dist: black (~=22.0) ; extra == 'dev'
Requires-Dist: coverage (==6.5) ; extra == 'dev'
